Workbook
Name start: FinModel!#REF!
Name start: [1]FinModel!#REF!
Name tax: [2]FinModel!$D$100

Sheet FinModel
A1: Novo Nordisk
A2: All in DKK'm unless otherwise specified
G5: Historical | J5: Forecast
G6: 2021A | H6: 2022A | I6: 2023A | J6: 2024E | K6: 2025E | L6: justification: | S6: Notes:
B8: Income Statement | L8: X
C9: Revenue | G9: 140800 | H9: 176954 | I9: 232261 | J9: =J132 -> 287792.06 | K9: =K132 -> 356574.36
C10: Cost of goods sold | G10: =G157+G158 -> -19978 | H10: =H157+H158 -> -24373 | I10: =I157+I158 -> -30815 | J10: =-J9*J151 -> -38910.98 | K10: =-K9*K151 -> -47759.429 | L10: adjusted excluding depreciation, amortisation, and impairment loss
B11: Gross Profit | G11: =G9+G10 -> 120822 | H11: =H9+H10 -> 152581 | I11: =I9+I10 -> 201446 | J11: =J9+J10 -> 248881.08 | K11: =K9+K10 -> 308814.93
C12: % margin | G12: =G11/G9 -> 0.8581108 | H12: =H11/H9 -> 0.86226364 | I12: =I11/I9 -> 0.86732598 | J12: =J11/J9 -> 0.86479481 | K12: =K11/K9 -> 0.8660604
C14: Administrative expenses | G14: =-4050+G159 -> -3653 | H14: =-4467+H159 -> -4040 | I14: =-4855+I159 -> -4460 | J14: =-J9*J152 -> -4892.465 | K14: =-K9*K152 -> -6061.7642 | L14: adjusted
C15: Sales and distribution costs | G15: =-37008+G160 -> -36560 | H15: =-46217+H160 -> -45759 | I15: =-56743+I160 -> -56230 | J15: =-J9*J153 -> -60436.333 | K15: =-K9*K153 -> -74880.616 | L15: ^
C16: Research and development costs | G16: =-17772+G161 -> -16292 | H16: =-24047+H161 -> -21761 | I16: =-32443+I161 -> -29373 | J16: =-J9*J154 -> -48924.65 | K16: =-K9*K154 -> -60617.642 | L16: ^
C17: Other operating income and expenses | G17: =332-G162 -> 352 | H17: =1034-H162 -> 1150 | I17: =119-I162 -> 604 | J17: -163 | K17: -163 | L17: ^ | M17: forecasting other operating income? H1 2024
C18: Depreciation and Impairment losses on PPE | G18: -4386 | H18: -5003 | I18: -6165 | J18: =J165 -> -8315.5561 | K18: =K165 -> -10746.174
C19: Amortisation and Impairment losses on Intangible asset | G19: -1639 | H19: -2359 | I19: -3248 | J19: -5700 | K19: =K166 -> -4069.6345 | L19: Exceptional Item: Impairment loss intangible asset Ocedurenone
C21: Total Depreciation, Amortisation, and Impairment losses | G21: =SUM(G18:G19) -> -6025 | H21: =SUM(H18:H19) -> -7362 | I21: =SUM(I18:I19) -> -9413 | J21: =SUM(J18:J19) -> -14015.556 | K21: =SUM(K18:K19) -> -14815.809
B22: Operating Profit | G22: =G11+SUM(G14:G19) -> 58644 | H22: =H11+SUM(H14:H19) -> 74809 | I22: =I11+SUM(I14:I19) -> 102574 | J22: =J11+SUM(J14:J19) -> 120449.08 | K22: =K11+SUM(K14:K19) -> 152276.1
B24: EBITDA | G24: =G22-G18-G19 -> 64669 | H24: =H22-H18-H19 -> 82171 | I24: =I22-I18-I19 -> 111987 | J24: =J22-J18-J19 -> 134464.63 | K24: =K22-K18-K19 -> 167091.91
C25: % margin | G25: =G24/G9 -> 0.45929687 | H25: =H24/H9 -> 0.46436362 | I25: =I24/I9 -> 0.48216016 | J25: =J24/J9 -> 0.46722843 | K25: =K24/K9 -> 0.46860327 | L25: so loww why | M25: spends record amounts on research to fend off rivals (on what?)
C27: Financial income | G27: 2887 | H27: 239 | I27: 2945 | J27: =I27 -> 2945 | K27: =J27 -> 2945 | L27: 2022 low bc no capital gains from forward contracts, investments, marketable securities
C28: Financial costs | G28: -2451 | H28: -5986 | I28: -845 | J28: =-J238 -> -1521.5037 | K28: =-K238 -> -1347.732
B29: PBT | G29: =G22+G27+G28 -> 59080 | H29: =H22+H27+H28 -> 69062 | I29: =I22+I27+I28 -> 104674 | J29: =J22+J27+J28 -> 121872.57 | K29: =K22+K27+K28 -> 153873.37
C31: Income tax expense | G31: -11323 | H31: -13537 | I31: -20991 | J31: =-J29*J228 -> -23155.789 | K31: =-K29*K228 -> -29235.941
B32: Profit for the period | G32: =G29+G31 -> 47757 | H32: =H29+H31 -> 55525 | I32: =I29+I31 -> 83683 | J32: =SUM(J29,J31) -> 98716.784 | K32: =SUM(K29,K31) -> 124637.43
C33: % margin | G33: =G32/G9 -> 0.33918324 | H33: =H32/H9 -> 0.31378211 | I33: =I32/I9 -> 0.36029725 | J33: =J32/J9 -> 0.34301427 | K33: =K32/K9 -> 0.3495412
B36: Balance Sheet
C37: Cash at bank | G37: 10720 | H37: 12653 | I37: 14392 | J37: =J125+327 -> 15881.674 | K37: =K125-6420 -> 16044.683
C38: Trade receivables | G38: 40643 | H38: 50560 | I38: 64770 | J38: =J9/J173 -> 81230.462 | K38: =K9/K173 -> 100037.09
C39: Tax receivables | G39: 1119 | H39: 940 | I39: 2423 | J39: =J9/J174 -> 2025.9504 | K39: =K9/K174 -> 2997.5611
C40: Other receivables and prepayments | G40: 5037 | H40: 6005 | I40: 8068 | J40: =J9/J175 -> 9880.3049 | K40: =K9/K175 -> 12313.548
C41: Inventory | G41: 19621 | H41: 24388 | I41: 31811 | J41: =-J10/J176 -> 39542.171 | K41: =-K10/K176 -> 48915.608
C42: Marketable securities | G42: 6765 | H42: 10921 | I42: 15838 | J42: =I42 -> 15838 | K42: =J42 -> 15838
C43: Derivative financial instruments | G43: 1690 | H43: 2727 | I43: 2344 | J43: =I43 -> 2344 | K43: =J43 -> 2344
B44: Total Current Assets | G44: =SUM(G37:G43) -> 85595 | H44: =SUM(H37:H43) -> 108194 | I44: =SUM(I37:I43) -> 139646 | J44: =SUM(J37:J43) -> 166742.56 | K44: =SUM(K37:K43) -> 198490.49
C46: Property, plant and equipment | G46: 55362 | H46: 66671 | I46: 90961 | J46: =J203 -> 116877.44 | K46: =K203 -> 155253.27 | L46: significant step up in CAPEX
C47: Intangible assets | G47: 43171 | H47: 51416 | I47: 60406 | J47: =J209 -> 69085.659 | K47: =K209 -> 77254.024
C48: Investments in associated companies | G48: 525 | H48: 327 | I48: 410 | J48: =I48 -> 410 | K48: =J48 -> 410
C49: Deferred income tax assets | G49: 8672 | H49: 13427 | I49: 20380 | J49: =I49 -> 20380 | K49: =J49 -> 20380
C50: Other receivables and prepayments | G50: 267 | H50: 206 | I50: 1430 | J50: =I50 -> 1430 | K50: =J50 -> 1430
C51: Other financial assets | G51: 916 | H51: 1016 | I51: 1253 | J51: 1521 | K51: =J51 -> 1521
B52: Total Non-Current Assets | G52: =SUM(G46:G51) -> 108913 | H52: =SUM(H46:H51) -> 133063 | I52: =SUM(I46:I51) -> 174840 | J52: =SUM(J46:J51) -> 209704.1 | K52: =SUM(K46:K51) -> 256248.29
B54: Total Assets | G54: =G44+G52 -> 194508 | H54: =H44+H52 -> 241257 | I54: =I44+I52 -> 314486 | J54: =J44+J52 -> 376446.67 | K54: =K44+K52 -> 454738.79
C56: Borrowings | G56: 13684 | H56: 1466 | I56: 6478 | J56: =I56 -> 6478 | K56: =J56 -> 6478
C57: Trade payables | G57: 8870 | H57: 15587 | I57: 25606 | J57: =-J10/J177 -> 28123.976 | K57: =-K10/K177 -> 36922.91
C58: Tax payables | G58: 3658 | H58: 7091 | I58: 7116 | J58: =-J10/J178 -> 10018.847 | K58: =-K10/K178 -> 11628.56
C59: Other liabilities | G59: 19600 | H59: 23606 | I59: 28705 | J59: =-J10/J179 -> 36952.531 | K59: =-K10/K179 -> 44918.229
C60: Derivative financial instruments | G60: 2184 | H60: 2903 | I60: 1272 | J60: =I60 -> 1272 | K60: =J60 -> 1272
C61: Provisions | G61: 51520 | H61: 70287 | I61: 100478 | J61: =I61 -> 100478 | K61: =J61 -> 100478
B62: Total Current Liabilities | G62: =SUM(G56:G61) -> 99516 | H62: =SUM(H56:H61) -> 120940 | I62: =SUM(I56:I61) -> 169655 | J62: =SUM(J56:J61) -> 183323.35 | K62: =SUM(K56:K61) -> 201697.7
C64: Borrowings | G64: 12961 | H64: 24318 | I64: 20528 | J64: =J234 -> 18475.2 | K64: =K234 -> 16073.424
C65: Deferred income tax liabilities | G65: 5271 | H65: 7061 | I65: 10162 | J65: =I65 -> 10162 | K65: =J65 -> 10162
C66: Retirement benefit obligations | G66: 1280 | H66: 762 | I66: 742 | J66: =I66 -> 742 | K66: =J66 -> 742
C67: Other liabilities | G67: 360 | H67: 100 | I67: 189 | J67: =I67 -> 189 | K67: =J67 -> 189
C68: Provisions | G68: 4374 | H68: 4590 | I68: 6649 | J68: =I68 -> 6649 | K68: =J68 -> 6649
B69: Total Non-Current Liabilities | G69: =SUM(G64:G68) -> 24246 | H69: =SUM(H64:H68) -> 36831 | I69: =SUM(I64:I68) -> 38270 | J69: =SUM(J64:J68) -> 36217.2 | K69: =SUM(K64:K68) -> 33815.424
B71: Total Liabilities | G71: =G62+G69 -> 123762 | H71: =H62+H69 -> 157771 | I71: =I62+I69 -> 207925 | J71: =SUM(J62,J69) -> 219540.55 | K71: =SUM(K62,K69) -> 235513.12
B73: Net Assets | G73: =G54-G71 -> 70746 | H73: =H54-H71 -> 83486 | I73: =I54-I71 -> 106561 | J73: =J54-J71 -> 156906.11 | K73: =K54-K71 -> 219225.66
C75: Share capital | G75: 462 | H75: 456 | I75: 451 | J75: =I75 -> 451 | K75: =J75 -> 451
C76: Treasury shares | G76: -6 | H76: -6 | I76: -5 | J76: =I76 -> -5 | K76: =J76 -> -5
C77: Retained earnings | G77: 72004 | H77: 80587 | I77: 104839 | J77: =J195 -> 155184.56 | K77: =K195 -> 217503.28
C78: Other reserves | G78: -1714 | H78: 2449 | I78: 1276 | J78: =I78 -> 1276 | K78: =J78 -> 1276
B79: Total Equity | G79: =SUM(G75:G78) -> 70746 | H79: =SUM(H75:H78) -> 83486 | I79: =SUM(I75:I78) -> 106561 | J79: =SUM(J75:J78) -> 156906.56 | K79: =SUM(K75:K78) -> 219225.28
G80: =G79-G73 -> 0 | H80: =H79-H73 -> 0 | I80: =I79-I73 -> 0 | J80: =J79-J73 -> 0.44933265 | K80: =K79-K73 -> -0.3891694
B82: Cash Flow Statement
B83: Net profit | G83: 47757 | H83: 55525 | I83: 83683 | J83: =J32 -> 98716.784 | K83: =K32 -> 124637.43
B84: Adjustments of non-cash items:
C85: Income taxes in the income statement | G85: 11323 | H85: 13537 | I85: 20991 | J85: =-J31 -> 23155.789 | K85: =-K31 -> 29235.941
C86: Depreciation, amortisation, and impairment losses | G86: 6025 | H86: 7362 | I86: 9413 | J86: =-J21 -> 14015.556 | K86: =-K21 -> 14815.809
C87: Other non-cash items | G87: 13416 | H87: 22310 | I87: 32382 | J87: 41433 | K87: 42176
C89: Change in working capital: | G89: =G97+G98 -> -9063 | H89: =H97+H98 -> -5336 | I89: =I97+I98 -> -12245 | J89: =SUM(J97:J98) -> -18905.431 | K89: =SUM(K97:K98) -> -17515.679 | L89: assumptions for adjustments***
C90: change in inventories | G90: -1085 | H90: -4767 | I90: -7423 | J90: =I41-J41 -> -7731.1715 | K90: =J41-K41 -> -9373.4367
C91: change in trade receivables | G91: -12909 | H91: -9917 | I91: -14210 | J91: =I38-J38 -> -16460.462 | K91: =J38-K38 -> -18806.631
C92: change in other receivables and prepayments | G92: -876 | H92: -968 | I92: -2063 | J92: =I40-J40 -> -1812.3049 | K92: =J40-K40 -> -2433.243
C93: change in trade payables | G93: 3153 | H93: 6717 | I93: 10019 | J93: =-(I57-J57) -> 2517.9763 | K93: =-(J57-K57) -> 8798.9337
C94: change in other liabilities | G94: 2595 | H94: 4006 | I94: 5099 | J94: =-(I59-J59) -> 8247.531 | K94: =-(J59-K59) -> 7965.6983
C95: adjustments for payables related to NCA | G95: -15 | H95: -1567 | I95: -2432 | J95: =I95 -> -2432 | K95: =J95 -> -2432
C96: adjustments related to acquisition of business | G96: -1409 | H96: -143 | I96: 0 | J96: 0 | K96: 0
C97: change in working capital including exchange rate adjustments | G97: =SUM(G90:G96) -> -10546 | H97: =SUM(H90:H96) -> -6639 | I97: =SUM(I90:I95) -> -11010 | J97: =SUM(J90:J95) -> -17670.431 | K97: =SUM(K90:K95) -> -16280.679
C98: exchange rate adjustments | G98: 1483 | H98: 1303 | I98: -1235 | J98: =I98 -> -1235 | K98: =J98 -> -1235
C100: Interest received | G100: 241 | H100: 276 | I100: 1072 | J100: =I100 -> 1072 | K100: =J100 -> 1072
C101: Interest paid | G101: -261 | H101: -272 | I101: -491 | J101: =I101 -> -491 | K101: =J101 -> -491
C102: Income taxes paid | G102: -14438 | H102: -14515 | I102: -25897 | J102: =I102 -> -25897 | K102: =J102 -> -25897
B104: Net Cash Flow from Operating Activities | G104: =SUM(G83,G85:G87,G89,G100:G102) -> 55000 | H104: =SUM(H83,H85:H87,H89,H100:H102) -> 78887 | I104: =SUM(I83,I85:I87,I89,I100:I102) -> 108908 | J104: =SUM(J83,J85:J87,J89,J100:J102) -> 133099.7 | K104: =SUM(K83,K85:K87,K89,K100:K102) -> 168033.5
C106: Purchase of intangible assets | G106: -1050 | H106: -2607 | I106: -13090 | J106: =-J207 -> -12238 | K106: =-K207 -> -12238
C107: Purchase of property, plant, and equipment | G107: -6335 | H107: -12146 | I107: -25806 | J107: =-J201 -> -34232 | K107: =-K201 -> -49122
C108: Cash used for acquisition of businesses | G108: -18283 | H108: -7075 | I108: 0 | J108: =I108 -> 0 | K108: =J108 -> 0
C109: Proceeds from other financial assets | G109: 0 | H109: 0 | I109: 33 | J109: 0 | K109: 0
C110: Purchase of other financial assets | G110: -4 | H110: -169 | I110: -271 | J110: =I110 -> -271 | K110: =J110 -> -271
C111: Purchase of marketable securities | G111: -7109 | H111: -9566 | I111: -13018 | J111: =I111 -> -13018 | K111: =J111 -> -13018
C112: Sale of marketable securities | G112: 1172 | H112: 6645 | I112: 8260 | J112: =I112 -> 8260 | K112: =J112 -> 8260
C113: Dividend received from associated companies | G113: 4 | H113: 0 | I113: 0 | J113: 0 | K113: 0
B114: Net Cash Flow from Investing Activities | G114: =SUM(G106:G113) -> -31605 | H114: =SUM(H106:H113) -> -24918 | I114: =SUM(I106:I113) -> -43892 | J114: =SUM(J106:J113) -> -51499 | K114: =SUM(K106:K113) -> -66389
C116: Purchase of treasury shares | G116: -19447 | H116: -24086 | I116: -29924 | J116: =I116 -> -29924 | K116: =J116 -> -29924
C117: Dividends paid | G117: -21517 | H117: -25303 | I117: -31767 | J117: =J194 -> -48371.224 | K117: =K194 -> -62318.715
C118: Proceeds from borrowings | G118: 22160 | H118: 11215 | I118: 0 | J118: =I118 -> 0 | K118: 0
C119: Repayment of borrowings | G119: -6689 | H119: -13623 | I119: -1467 | J119: =J232 -> -2052.8 | K119: =K232 -> -2401.776
B120: Net Cash Flow from Financing Activities | G120: =SUM(G116:G119) -> -25493 | H120: =SUM(H116:H119) -> -51797 | I120: =SUM(I116:I119) -> -63158 | J120: =SUM(J116:J119) -> -80348.024 | K120: =SUM(K116:K119) -> -94644.491
B122: Net change in cash | G122: =SUM(G104,G114,G120) -> -2098 | H122: =SUM(H104,H114,H120) -> 2172 | I122: =SUM(I104,I114,I120) -> 1858 | J122: =SUM(J120,J114,J104) -> 1252.6737 | K122: =SUM(K120,K114,K104) -> 7000.0096
B123: Cash & cash equivalents at the beginning of the year | G123: 12226 | H123: =G125 -> 10719 | I123: =H125 -> 12653 | J123: =I125 -> 14392 | K123: =J125 -> 15554.674
B124: Exchange gains/ (losses) on cash and cash equivalents | G124: 591 | H124: -238 | I124: -119 | J124: -90 | K124: =J124 -> -90
...

Sheet Valuation 10y
A1: Novo Nordisk
A6: FCFE method | D6: 0 | E6: 1 | F6: 2 | G6: 3 | H6: 4 | I6: 5 | J6: 6 | K6: 7 | L6: 8 | M6: 9 | N6: 10 | P6: Risk-free rate (DK10-Year Govt Bond Yield) | Q6: 0.02206
B7: In DKK mil | D7: 2023 | E7: 2024 | F7: 2025 | G7: 2026 | H7: 2027 | I7: 2028 | J7: 2029 | K7: 2030 | L7: 2031 | M7: 2032 | N7: 2033 | P7: Beta (vs. OMXC25) | Q7: 0.88
B8: CFO | D8: =FinModel!I104 -> 108908 | E8: =FinModel!J104 -> 133099.7 | F8: =FinModel!K104 -> 168033.5 | G8: =F8*(1+Q11) -> 171058.1 | H8: =G8*(1+Q11) -> 174137.15 | I8: =H8*(1+$Q$11) -> 177271.62 | J8: =I8*(1+$Q$11) -> 180462.51 | K8: =J8*(1+$Q$11) -> 183710.83 | L8: =K8*(1+$Q$11) -> 187017.63 | M8: =L8*(1+$Q$11) -> 190383.95 | N8: =M8*(1+$Q$11) -> 193810.86 | P8: Market return (Rm) | Q8: 0.0457
B9: (CAPEX) | D9: =FinModel!I107+FinModel!I106 -> -38896 | E9: =FinModel!J107+FinModel!J106 -> -46470 | F9: =FinModel!K107+FinModel!K106 -> -61360 | G9: =F9 -> -61360 | H9: =G9 -> -61360 | I9: =H9 -> -61360 | J9: =I9 -> -61360 | K9: =J9 -> -61360 | L9: =K9 -> -61360 | M9: =L9 -> -61360 | N9: =M9 -> -61360 | P9: Cost of Equity | Q9: =Q6+(Q7*(Q8-Q6)) -> 0.0428632
B10: FCFE | D10: =D8+D9 -> 70012 | E10: =E8+E9 -> 86629.698 | F10: =F8+F9 -> 106673.5 | G10: =G8+G9 -> 109698.1 | H10: =H8+H9 -> 112777.15 | I10: =I8+I9 -> 115911.62 | J10: =J8+J9 -> 119102.51 | K10: =K8+K9 -> 122350.83 | ... N10: =N8+N9 -> 132450.86
B11: Discount factor | D11: =1/(1+$T$41)^D6 -> 1 | E11: =1/(1+$T$41)^E6 -> 0.959007 | F11: =1/(1+$T$41)^F6 -> 0.91969442 | G11: =1/(1+$T$41)^G6 -> 0.88199338 | H11: =1/(1+$T$41)^H6 -> 0.84583782 | I11: =1/(1+$T$41)^I6 -> 0.81116439 | J11: =1/(1+$T$41)^J6 -> 0.77791232 | K11: =1/(1+$T$41)^K6 -> 0.74602336 | ... N11: =1/(1+$T$41)^N6 -> 0.65798767 | P11: LT growth (inflation % yoy) | Q11: 0.018
B12: PV | D12: =D11*D10 -> 70012 | E12: =E11*E10 -> 83078.486 | F12: =F11*F10 -> 98107.023 | G12: =G11*G10 -> 96753.002 | H12: =H11*H10 -> 95391.179 | I12: =I11*I10 -> 94023.377 | J12: =J11*J10 -> 92651.308 | K12: =K11*K10 -> 91276.579 | ... N12: =N11*N10 -> 87151.03
P14: Total Debt | Q14: =FinModel!I56+FinModel!I64 -> 27006
P15: Market Value of Debt
B16: Sum of PV | D16: =SUM(D12:N12) -> 986869.75 | P16: Cost of debt | Q16: =FinModel!I238/'Valuation 10y'!Q14 -> 0.031289343
B17: Terminal value | D17: =(N10*(1+Q11))/(Q9-Q11) -> 5423073.9
B18: PV of terminal value | D18: =D17/(1+Q9)^10 -> 3564282.3 | P18: Tax rate | Q18: =-FinModel!I228 -> 0.20053691
B19: Equity Value (DKK mil) | D19: =D18+D16 -> 4551152.1
B21: Target Price: | D21: =D19/4465 -> 1019.295
B22: Upside: | D22: =D21/912-1 -> 0.11764801
P23: WACC = % of equity x cost of equity + % of debt x cost of debt x (1 - Tax Rate)
P24: Cost of equity = Risk free rate + Beta x Market Risk Premium
B25: Calculating Equity IRR
B26: In DKK mil | D26: 2019 | E26: 2020 | F26: 2021 | G26: 2022 | H26: 2023 | I26: 2024 | J26: 2025 | K26: Terminal Value | P26: WACC
B27: Outlay | D27: =-D35 -> -4045608 | P27: Market Cap (DKK) | T27: 4060000000000 | U27: 4060000 | V27: million
B28: FCFE | E28: =D10 -> 70012 | F28: =E10 -> 86629.698 | G28: =F10 -> 106673.5 | H28: =G10 -> 109698.1 | I28: =H10 -> 112777.15 | J28: =I10 -> 115911.62 | K28: =D17 -> 5423073.9 | P28: % of Equity | T28: =T27/(T27+T34) -> 0.99339223
P29: Cost of Equity | T29: =T30+T31*T32 -> 0.0428632
P30: Risk Free Rate | T30: =Q6 -> 0.02206
B31: Proposed EV/EBITDA (X) | P31: Beta | T31: =Q7 -> 0.88
B32: 2018 EBITDA | P32: Market Risk Premium | T32: =Q8-Q6 -> 0.02364
B33: Enterprise Value | D33: =U27+Q14-FinModel!I37 -> 4072614 | E33: EV= market cap + debt - cash
B34: Less: Debt | D34: =-Q14 -> -27006 | P34: Debt | T34: 27006000000
B35: Equity Value (DKK mil) | D35: =D33+D34 -> 4045608 | P35: % of Debt | T35: =T34/(T27+T34) -> 0.0066077711
P36: Cost of Debt | T36: =Q16 -> 0.031289343
B37: Equity IRR | D37: =IRR(D27:K28) -> 0.061843826 | P37: Tax Rate | T37: =Q18 -> 0.20053691
G39: 5 years: | H39: 545982.68 | P39: Total | T39: =T27+T34 -> 4087006000000
B40: Multiple Method | G40: tv | H40: 4442012
G41: pv | H41: 3595355.4 | P41: WACC | T41: =T28*T29+(T35*T36*(1-T37)) -> 0.042745261
B42: Companies with most similair EBITDA margin to WidgePro | G42: equity value | H42: =H39+H41 -> 4141338.1
B43: Comp | C43: 2021 PE Multiple | D43: 2021 EV EBITDA multiple | E43: ebitda margin | H43: =H42/4465 -> 927.51134
B44: A | C44: 14.56 | D44: 9.95 | E44: 0.29874316 | H44: =H43/912-1 -> 0.017008043
B45: C | C45: 11.864 | D45: 9.679 | E45: 0.31191272
B46: E | C46: 8.078 | D46: 4.002 | E46: 0.31336712
B47: G | C47: 11.766 | D47: 5.931 | E47: 0.2851746
B48: L | C48: 14.259 | D48: 10.425 | E48: 0.31532794
B49: D | C49: 14.426 | D49: 8.965 | E49: 0.24619148
B50: Average | C50: =AVERAGE(C44:C49) -> 12.492167 | D50: =AVERAGE(D44:D49) -> 8.1586667 | E50: =AVERAGE(E44:E49) -> 0.2951195
B52: EV/EBITDA target multiple
B53: Widgepro's 2021 EBITDA | C53: =[3]FinModel!K21 -> 10.423915
B54: Target EV/EBITDA (based on peer group w similair margin, X) | C54: =D50 -> 8.1586667
B55: Enterprise Value | C55: =C53*C54 -> 85.045249
B56: 2021 debt | C56: =[3]FinModel!K49 -> 26.4495
B57: Equity value (USD mil) | C57: =C55-C56 -> 58.595749
B60: PER target multiple
B61: Widgepro's 2021 Earnings (USD mil) | C61: =[3]FinModel!K29 -> 6.2350906
B62: target PER (based on peer group with similair margin, X) | C62: =C50 -> 12.492167
B63: Equity Value (USD mil) | C63: =C61*C62 -> 77.889791

Sheet Ratio
A1: Financial Data | B1: 2021 | C1: 2022 | D1: 2023 | E1: 2024 | F1: 2025 | G1: 2026
A2: Revenue (Million Euros) | E2: 37959 | F2: 40152 | G2: 42492
A3: Revenue Growth | E3: 0.0573 | F3: 0.0578 | G3: 0.0583
A4: EBITDA (Million Euros) | E4: 7848 | F4: 8337 | G4: 8837
A5: EBIT (Million Euros) | E5: 6415 | F5: 6937 | G5: 7466
A6: PBT (Million Euros) | E6: 5950 | F6: 6505 | G6: 7063
A7: PATAMI (Million Euros) | E7: 3915 | F7: 4341 | G7: 4769
A8: EPS | E8: 8.25 | F8: 9.02 | G8: 9.78
A9: BVPS | E9: 52.64 | F9: 57.13 | G9: 62
A10: GDPS | E10: 4.14 | F10: 4.53 | G10: 4.91
A11: CFO | E11: 6330 | F11: 6082 | G11: 6458
A12: FCF | E12: 5132 | F12: 4884 | G12: 5260
A13: Key Ratios | B13: 2021 | C13: 2022 | D13: 2023 | E13: 2024 | F13: 2025 | G13: 2026
A14: PER (x) | E14: 27.49 | F14: 25.17 | G14: 23.2
A15: PTBV (x) | E15: 4.31 | F15: 3.97 | G15: 3.66
A16: Div. yield (%) | E16: 0.0183 | F16: 0.0199 | G16: 0.0216
A17: Div. payout (%) | E17: 0.502 | F17: 0.502 | G17: 0.502
A18: EBITDA margin (%) | E18: 0.2067 | F18: 0.2076 | G18: 0.208
A19: EBIT margin (%) | E19: 0.169 | F19: 0.1728 | G19: 0.1757
A20: PBT margin (%) | E20: 0.1568 | F20: 0.162 | G20: 0.1662
A21: PATAMI margin (%) | E21: 0.1031 | F21: 0.1081 | G21: 0.1122
A22: ROE (%) | E22: 0.1568 | F22: 0.1578 | G22: 0.1577
A23: ROA (%) | E23: 0.0763 | F23: 0.0806 | G23: 0.0843
A24: Net debt (Million Euros) | E24: 6466 | F24: 4115 | G24: 1604
A25: Net gearing (x) | E25: 0.43 | F25: 0.37 | G25: 0.31
A26: FCF yield (%) | E26: 0.0404 | F26: 0.0384 | G26: 0.0414
A28: Total Number of shares | E28: 3.4 billion
A29: Average Share Price | B29: 226.9 | C29: 226.9 | D29: 226.9 | E29: 226.9 | F29: 226.9 | G29: 226.9
A31: historical, key financial highlights, forward looking too
A33: current outstanding shares: 4465 million as of June 2024

Sheet CCA
B3: sales by segment | G3: sales by region | I3: Mainland China, Hong Kong and Taiwan | J3: Rest of World: All other countries except for North America.
B4: Diabetes and Obesity Care | C4: 0.93 | G4: EMEA | H4: North America Operations | I4: China | J4: Rest of the world
B5: Rare Disease | C5: 0.07 | G5: 50867 | H5: 136629 | I5: 16687 | J5: 28078 | K5: =G5+H5+I5+J5 -> 232261
G6: =G5/$K$5*100 -> 21.900793 | H6: =H5/$K$5*100 -> 58.825632 | I6: =I5/$K$5*100 -> 7.1845898 | J6: =J5/$K$5*100 -> 12.088986
B7: 0.93 | C7: 0.07
B8: 215098 | C8: 17163 | D8: =B8+C8 -> 232261 | G8: =FinModel!K104 -> 168033.5 | H8: =G8*(1+O14) -> 168033.5
F11: =1/(1+$O$12)^F6 -> 1
E16: =SUM(E12:K12) -> 0
E17: =(K10*(1+O14))/(O12-O14) -> #DIV/0!
E18: =E17/(1+O12)^6 -> #DIV/0!
E19: =E18+E16 -> #DIV/0!
B25: earnings per share ratio | I25: P/E ratio comparison with competitors | K25: source: yahoo finance
B26: year | C26: 2019 | D26: 2020 | E26: 2021 | F26: 2022 | G26: 2023 | I26: companies | J26: AstraZeneca | K26: Sanofi | L26: Novo Nordisk | M26: Eli Lilly
B27: earnings per share | C27: 8.19 | D27: 9.01 | E27: 10.37 | F27: 12.22 | G27: 18.62 | I27: P/E ratio | J27: 39.19 | K27: 21.46 | L27: 46.37 | M27: 85.2
B28: % change | D28: =(D27-C27)/C27 -> 0.1001221 | E28: =(E27-D27)/D27 -> 0.1509434 | F28: =(F27-E27)/E27 -> 0.17839923 | G28: =(G27-F27)/F27 -> 0.52373159
C30: 2018
C31: 18.05
F45: why did EPS steeply increased from 2022 to 2023 | J45: why does P/E ratio differ so much?
F46: increase demand for ozempic, supply unable to keep up so causes limited supply.
B48: sales growth (DKK million) | J48: bigger company generally means bigger PE
B49: year | C49: 2019 | D49: 2020 | E49: 2021 | F49: 2022 | G49: 2023 | H49: what caused this sales growth?
B50: sales | C50: 122021 | D50: 126946 | E50: 140800 | F50: 176954 | G50: 232261 | H50: from 2022 to 2023???
B51: % change | C51: 0.091 | D51: =D53/100 -> 0.040361905 | E51: =E53/100 -> 0.10913302 | F51: =F53/100 -> 0.25677557 | G51: =G53/100 -> 0.31255015
D53: =((D50-C50)/C50)*100 -> 4.0361905 | E53: =((E50-D50)/D50)*100 -> 10.913302 | F53: =((F50-E50)/E50)*100 -> 25.677557 | G53: =((G50-F50)/F50)*100 -> 31.255015
C54: 0.091 | D54: 0.04 | E54: 0.109 | F54: 0.257 | G54: 0.313
C55: 2018
J57: diabetes drug market
J58: year | K58: 2023 | L58: 2032
J59: market value | K59: 66b | L59: 118b
B74: sales by business segment
H76: Column1 | I76: Column2 | J76: Column3

Sheet Valuation
A1: Novo Nordisk
N5: Discount Rate (cost of equity) Calculation
B6: FCFE method | E6: 0 | F6: 1 | G6: 2 | H6: 3 | I6: 4 | J6: 5
C7: In DKK mil | E7: 2023 | F7: 2024 | G7: 2025 | H7: 2026 | I7: 2027 | J7: 2028
C8: CFO | E8: =FinModel!I104 -> 108908 | F8: =FinModel!J104 -> 133099.7 | G8: =FinModel!K104 -> 168033.5 | H8: =G8*(1+O14) -> 171058.1 | I8: =H8*(1+O14) -> 174137.15 | J8: =I8*(1+$O$14) -> 177271.62
C9: (CAPEX) | E9: =FinModel!I107+FinModel!I106 -> -38896 | F9: =FinModel!J107+FinModel!J106 -> -46470 | G9: =FinModel!K107+FinModel!K106 -> -61360 | H9: =G9 -> -61360 | I9: =H9 -> -61360 | J9: =I9 -> -61360 | N9: Risk-free rate (DK10-Year Govt Bond Yield) | O9: 0.02206
C10: FCFE | E10: =E8+E9 -> 70012 | F10: =F8+F9 -> 86629.698 | G10: =G8+G9 -> 106673.5 | H10: =H8+H9 -> 109698.1 | I10: =I8+I9 -> 112777.15 | J10: =J8+J9 -> 115911.62 | N10: Beta (vs. OMXC25) | O10: 0.88
C11: Discount factor | E11: =1/(1+$O$12)^E6 -> 1 | F11: =1/(1+$O$12)^F6 -> 0.95889854 | G11: =1/(1+$O$12)^G6 -> 0.91948641 | H11: =1/(1+$O$12)^H6 -> 0.88169418 | I11: =1/(1+$O$12)^I6 -> 0.84545526 | J11: =1/(1+$O$12)^J6 -> 0.81070581 | N11: Market return (Rm) | O11: 0.0457
C12: PV | E12: =E11*E10 -> 70012 | F12: =F11*F10 -> 83069.091 | G12: =G11*G10 -> 98084.834 | H12: =H11*H10 -> 96720.179 | I12: =I11*I10 -> 95348.034 | J12: =J11*J10 -> 93970.223 | N12: Cost of Equity | O12: =O9+(O10*(O11-O9)) -> 0.0428632
N14: LT growth (inflation % yoy) | O14: 0.018
C16: Sum of PV | E16: =SUM(E12:J12) -> 537204.36
C17: Terminal value | E17: =(J10*(1+O14))/(O12-O14) -> 4745890.6 | N17: Total Debt | O17: =FinModel!I56+FinModel!I64 -> 27006
C18: PV of terminal value | E18: =E17/(1+O12)^5 -> 3847521.1 | N18: Market Value of Debt
C19: Equity Value (DKK mil) | E19: =E18+E16 -> 4384725.5 | N19: Cost of debt | O19: =FinModel!I238/Valuation!O17 -> 0.031289343
C21: Target Price: | E21: =E19/4465 -> 982.02138 | N21: Tax rate | O21: =-FinModel!I228 -> 0.20053691
C22: Upside: | E22: =E21/912-1 -> 0.076777833
N23: WACC
C25: Calculating Equity IRR
C26: In DKK mil | E26: 2019 | F26: 2020 | G26: 2021 | H26: 2022 | I26: 2023 | J26: 2024 | K26: 2025 | L26: Terminal Value
C27: Outlay | E27: =-E35 -> -77.731
C28: FCFE | F28: =E10 -> 70012 | G28: =F10 -> 86629.698 | H28: =G10 -> 106673.5 | I28: =H10 -> 109698.1 | J28: =I10 -> 112777.15 | K28: =J10 -> 115911.62 | L28: =E17 -> 4745890.6
C30: Seller's propossal
C31: Proposed EV/EBITDA (X) | E31: 13
C32: 2018 EBITDA | E32: =[3]FinModel!H21 -> 6.51
C33: Enterprise Value | E33: =E31*E32 -> 84.63
C34: Less: Debt | E34: =-[3]FinModel!H49 -> -6.899
C35: Equity Value (USD mil) | E35: =E33+E34 -> 77.731
C37: Equity IRR | E37: =IRR(E27:L28) -> 900.93334
H39: 5 years: | I39: 545982.68
C40: Multiple Method | H40: tv | I40: 4442012
H41: pv | I41: 3595355.4
C42: Companies with most similair EBITDA margin to WidgePro | H42: equity value | I42: =I39+I41 -> 4141338.1
C43: Comp | D43: 2021 PE Multiple | E43: 2021 EV EBITDA multiple | F43: ebitda margin | I43: =I42/4465 -> 927.51134
C44: A | D44: 14.56 | E44: 9.95 | F44: 0.29874316 | I44: =I43/912-1 -> 0.017008043
C45: C | D45: 11.864 | E45: 9.679 | F45: 0.31191272
C46: E | D46: 8.078 | E46: 4.002 | F46: 0.31336712
C47: G | D47: 11.766 | E47: 5.931 | F47: 0.2851746
C48: L | D48: 14.259 | E48: 10.425 | F48: 0.31532794
C49: D | D49: 14.426 | E49: 8.965 | F49: 0.24619148
C50: Average | D50: =AVERAGE(D44:D49) -> 12.492167 | E50: =AVERAGE(E44:E49) -> 8.1586667 | F50: =AVERAGE(F44:F49) -> 0.2951195
C52: EV/EBITDA target multiple
C53: Widgepro's 2021 EBITDA | D53: =[3]FinModel!K21 -> 10.423915
C54: Target EV/EBITDA (based on peer group w similair margin, X) | D54: =E50 -> 8.1586667
C55: Enterprise Value | D55: =D53*D54 -> 85.045249
C56: 2021 debt | D56: =[3]FinModel!K49 -> 26.4495
C57: Equity value (USD mil) | D57: =D55-D56 -> 58.595749
C60: PER target multiple
C61: Widgepro's 2021 Earnings (USD mil) | D61: =[3]FinModel!K29 -> 6.2350906
C62: target PER (based on peer group with similair margin, X) | D62: =D50 -> 12.492167
C63: Equity Value (USD mil) | D63: =D61*D62 -> 77.889791
